client_for_tvdb/__init__.py
client_for_tvdb/client.py
client_for_tvdb/config.py
client_for_tvdb/end_points.py
client_for_tvdb/exceptions.py
client_for_tvdb-2020.5.24.dist-info/LICENSE.md
client_for_tvdb-2020.5.24.dist-info/WHEEL
client_for_tvdb-2020.5.24.dist-info/METADATA
client_for_tvdb-2020.5.24.dist-info/RECORD
