Metadata-Version: 2.1
Name: client-for-tvdb
Version: 2020.5.24
Summary: A simple client for the TVDB API v3.
Home-page: https://github.com/opacam/client-for-tvdb/
License: MIT
Keywords: tvdb,API client
Author: opacam
Author-email: canellestudi@gmail.com
Maintainer: opacam
Maintainer-email: canellestudi@gmail.com
Requires-Python: >=3.6,<4.0
Classifier: Development Status :: 4 - Beta
Classifier: License :: OSI Approved :: MIT License
Classifier: Operating System :: POSIX
Classifier: Operating System :: POSIX :: Linux
Classifier: Programming Language :: Python :: 3
Classifier: Programming Language :: Python :: 3.6
Classifier: Programming Language :: Python :: 3.7
Classifier: Programming Language :: Python :: 3.8
Classifier: Topic :: Multimedia :: Video
Classifier: Topic :: Utilities
Requires-Dist: python-dotenv (>=0.13.0,<0.14.0)
Requires-Dist: requests (>=2.23.0,<3.0.0)
Requires-Dist: requests-cache (>=0.5.2,<0.6.0)
Project-URL: Repository, https://github.com/opacam/client-for-tvdb/
